Metadata-Version: 1.1
Name: django-wallets
Version: 0.1.41
Summary: BTC, LTC, DASH, DOGE wallets for each user with withdraw with webhook
Home-page: https://github.com/narnikgamarnikus/django-wallets
Author: Vladimir Myshkovski
Author-email: vladimirmyshkovski@gmail.com
License: MIT
Keywords: django-wallets
Platform: UNKNOWN
Classifier: Development Status :: 3 - Alpha
Classifier: Framework :: Django
Classifier: Framework :: Django :: 1.10
Classifier: Intended Audience :: Developers
Classifier: License :: OSI Approved :: BSD License
Classifier: Natural Language :: English
Classifier: Programming Language :: Python :: 2
Classifier: Programming Language :: Python :: 2.7
Classifier: Programming Language :: Python :: 3
Classifier: Programming Language :: Python :: 3.4
Classifier: Programming Language :: Python :: 3.5
